mujoco_viewer/__init__.py
mujoco_viewer/callbacks.py
mujoco_viewer/mujoco_viewer.py
mujoco_python_viewer-0.1.4.dist-info/LICENSE
mujoco_python_viewer-0.1.4.dist-info/METADATA
mujoco_python_viewer-0.1.4.dist-info/WHEEL
mujoco_python_viewer-0.1.4.dist-info/top_level.txt
mujoco_python_viewer-0.1.4.dist-info/RECORD
