Metadata-Version: 2.1
Name: mujoco-python-viewer
Version: 0.1.4
Summary: Interactive renderer for MuJoCo Python
Home-page: https://github.com/rohanpsingh/mujoco-python-viewer
Author: Rohan P. Singh
Author-email: rohan565singh@gmail.com
Classifier: Programming Language :: Python :: 3
Classifier: Programming Language :: Python :: 3.6
Classifier: Programming Language :: Python :: 3.7
Classifier: Programming Language :: Python :: 3 :: Only
Requires-Python: >=3.6
License-File: LICENSE
Requires-Dist: mujoco>=2.1.5
Requires-Dist: glfw>=2.5.0
Requires-Dist: imageio
Requires-Dist: pyyaml
